[{"_id":"630292bbd549dbed000a4895","name":"Mobiles,Computers","__v":0},{"_id":"630292dcd549dbed000a4897","name":"TV appliances electronics","__v":0},{"_id":"630292ecd549dbed000a4899","name":"Men Fashion","__v":0},{"_id":"63029318d549dbed000a489b","name":"All Mobile Phones","parent":"630292bbd549dbed000a4895","__v":0},{"_id":"63029348d549dbed000a489d","name":"All Mobile Accessories","parent":"630292bbd549dbed000a4895","__v":0},{"_id":"63029359d549dbed000a489f","name":"Case Covers","parent":"630292bbd549dbed000a4895","__v":0},{"_id":"63029386d549dbed000a48a1","name":"Smart Phones","parent":"63029318d549dbed000a489b","__v":0},{"_id":"63029393d549dbed000a48a3","name":"Basic Phones","parent":"63029318d549dbed000a489b","__v":0},{"_id":"6302939fd549dbed000a48a5","name":"Android","parent":"63029318d549dbed000a489b","__v":0}]